{"version": 0.6, "generator": "Overpass API 0.7.62.7 375dc00a", "osm3s": {"timestamp_osm_base": "2025-07-03T14:39:09Z", "copyright": "The data included in this document is from www.openstreetmap.org. The data is made available under ODbL."}, "elements": [{"type": "node", "id": 288273500, "lat": 47.5709721, "lon": 7.566296, "tags": {"access": "customers", "amenity": "parking", "fee": "yes", "parking": "surface", "source": "image"}}, {"type": "node", "id": 299854016, "lat": 47.5817407, "lon": 7.5713729}, {"type": "node", "id": 309169828, "lat": 47.5792004, "lon": 7.5726028}, {"type": "node", "id": 309169830, "lat": 47.5789406, "lon": 7.5724372}, {"type": "node", "id": 309169832, "lat": 47.5787663, "lon": 7.5725832}, {"type": "node", "id": 309169834, "lat": 47.5787465, "lon": 7.5730246}, {"type": "node", "id": 309169876, "lat": 47.5803331, "lon": 7.5721188}, {"type": "node", "id": 357561889, "lat": 47.5778849, "lon": 7.5691578}, {"type": "node", "id": 357561910, "lat": 47.5780576, "lon": 7.568202}, {"type": "node", "id": 357561913, "lat": 47.5780988, "lon": 7.5682922}, {"type": "node", "id": 357561915, "lat": 47.578137, "lon": 7.5694847}, {"type": "node", "id": 357561966, "lat": 47.5797691, "lon": 7.5662198}, {"type": "node", "id": 357561969, "lat": 47.5796321, "lon": 7.5663248}, {"type": "node", "id": 357561972, "lat": 47.5805198, "lon": 7.5683863}, {"type": "node", "id": 357561974, "lat": 47.5806511, "lon": 7.5682604}, {"type": "node", "id": 726285689, "lat": 47.5661077, "lon": 7.5731529}, {"type": "node", "id": 1189453586, "lat": 47.5770581, "lon": 7.5623592}, {"type": "node", "id": 1189453594, "lat": 47.5789057, "lon": 7.5619059}, {"type": "node", "id": 1189453600, "lat": 47.576589, "lon": 7.5638811}, {"type": "node", "id": 1189453601, "lat": 47.578571, "lon": 7.5604826}, {"type": "node", "id": 1189453603, "lat": 47.5778387, "lon": 7.5623411}, {"type": "node", "id": 1189453606, "lat": 47.5790843, "lon": 7.5615767}, {"type": "node", "id": 1189453608, "lat": 47.5772647, "lon": 7.5616767}, {"type": "node", "id": 1189453610, "lat": 47.5780657, "lon": 7.5605468}, {"type": "node", "id": 1189453612, "lat": 47.5764675, "lon": 7.5628416}, {"type": "node", "id": 1189453638, "lat": 47.578559, "lon": 7.5619479}, {"type": "node", "id": 1189453646, "lat": 47.5765777, "lon": 7.5624066}, {"type": "node", "id": 1189453657, "lat": 47.5776609, "lon": 7.5611069}, {"type": "node", "id": 1189453664, "lat": 47.5762742, "lon": 7.5624022}, {"type": "node", "id": 1189453681, "lat": 47.5789976, "lon": 7.561818}, {"type": "node", "id": 1189453687, "lat": 47.5784849, "lon": 7.5605295}, {"type": "node", "id": 1189453691, "lat": 47.5764713, "lon": 7.563885}, {"type": "node", "id": 1189453705, "lat": 47.5790762, "lon": 7.5612308}, {"type": "node", "id": 1189453709, "lat": 47.5779997, "lon": 7.5621073}, {"type": "node", "id": 1189453721, "lat": 47.5770396, "lon": 7.5619601}, {"type": "node", "id": 1189453725, "lat": 47.5779787, "lon": 7.5606243}, {"type": "node", "id": 1189453732, "lat": 47.5762726, "lon": 7.5627837}, {"type": "node", "id": 1259891366, "lat": 47.5778814, "lon": 7.5744933}, {"type": "node", "id": 1559474231, "lat": 47.5792966, "lon": 7.5656732}, {"type": "node", "id": 1559474486, "lat": 47.5793932, "lon": 7.5655193}, {"type": "node", "id": 1559474524, "lat": 47.5794149, "lon": 7.5655789}, {"type": "node", "id": 1559474699, "lat": 47.5795161, "lon": 7.5654214}, {"type": "node", "id": 1559474875, "lat": 47.5796197, "lon": 7.5657069}, {"type": "node", "id": 1560717242, "lat": 47.583253, "lon": 7.5658692}, {"type": "node", "id": 1579271743, "lat": 47.5767816, "lon": 7.5629627}, {"type": "node", "id": 1579271745, "lat": 47.5772581, "lon": 7.5629685}, {"type": "node", "id": 1579271747, "lat": 47.5773019, "lon": 7.5643597}, {"type": "node", "id": 1579281170, "lat": 47.5757949, "lon": 7.5623304}, {"type": "node", "id": 1579281171, "lat": 47.575804, "lon": 7.5632722}, {"type": "node", "id": 1579281189, "lat": 47.5760748, "lon": 7.5623244}, {"type": "node", "id": 1579281191, "lat": 47.5760839, "lon": 7.5632663}, {"type": "node", "id": 1579328506, "lat": 47.5824996, "lon": 7.5771427}, {"type": "node", "id": 1579328507, "lat": 47.5825126, "lon": 7.5769873}, {"type": "node", "id": 1579328508, "lat": 47.582688, "lon": 7.576435}, {"type": "node", "id": 1579328511, "lat": 47.5829604, "lon": 7.5778738}, {"type": "node", "id": 1579328523, "lat": 47.5834436, "lon": 7.5770139}, {"type": "node", "id": 1579334179, "lat": 47.5715949, "lon": 7.5814966, "tags": {"access": "customers", "amenity": "parking", "fee": "no", "layer": "-1", "name": "WSJ-209", "operator": "Novartis", "parking": "underground"}}, {"type": "node", "id": 1637902901, "lat": 47.5805935, "lon": 7.5683156}, {"type": "node", "id": 1892331309, "lat": 47.5814036, "lon": 7.57544}, {"type": "node", "id": 1892331313, "lat": 47.5811892, "lon": 7.5756045}, {"type": "node", "id": 1892331337, "lat": 47.5811778, "lon": 7.575489}, {"type": "node", "id": 1892331338, "lat": 47.581415, "lon": 7.5755555}, {"type": "node", "id": 1892331339, "lat": 47.5811378, "lon": 7.5757962}, {"type": "node", "id": 1892331341, "lat": 47.5812154, "lon": 7.5742665}, {"type": "node", "id": 1892331347, "lat": 47.5814741, "lon": 7.5743094}, {"type": "node", "id": 1892331350, "lat": 47.5814632, "lon": 7.5742021}, {"type": "node", "id": 1892331375, "lat": 47.5811171, "lon": 7.5735301}, {"type": "node", "id": 1892331378, "lat": 47.5810049, "lon": 7.5731065}, {"type": "node", "id": 1892331381, "lat": 47.581171, "lon": 7.573477}, {"type": "node", "id": 1892331390, "lat": 47.580951, "lon": 7.5731596}, {"type": "node", "id": 1892331396, "lat": 47.5811177, "lon": 7.5756227}, {"type": "node", "id": 1892331400, "lat": 47.5812298, "lon": 7.5743697}, {"type": "node", "id": 1911101327, "lat": 47.5810965, "lon": 7.5739218}, {"type": "node", "id": 1940503453, "lat": 47.5783192, "lon": 7.5720783}, {"type": "node", "id": 1940503455, "lat": 47.5785394, "lon": 7.5694641}, {"type": "node", "id": 1940503458, "lat": 47.5784218, "lon": 7.5728115}, {"type": "node", "id": 1940503478, "lat": 47.5782499, "lon": 7.5721228}, {"type": "node", "id": 1940503485, "lat": 47.5781313, "lon": 7.5681417}, {"type": "node", "id": 1940503489, "lat": 47.5787304, "lon": 7.5691415}, {"type": "node", "id": 1940503496, "lat": 47.5781729, "lon": 7.5682577}, {"type": "node", "id": 1940503507, "lat": 47.5785919, "lon": 7.5737851}, {"type": "node", "id": 1940503510, "lat": 47.5787726, "lon": 7.5692361}, {"type": "node", "id": 1940503514, "lat": 47.5783747, "lon": 7.5723474}, {"type": "node", "id": 1940503523, "lat": 47.5783983, "lon": 7.5728302}, {"type": "node", "id": 1940503525, "lat": 47.5791888, "lon": 7.572265}, {"type": "node", "id": 1940503538, "lat": 47.5791439, "lon": 7.5721631}, {"type": "node", "id": 1940503541, "lat": 47.5783295, "lon": 7.5722106}, {"type": "node", "id": 1940503543, "lat": 47.578353, "lon": 7.5721945}, {"type": "node", "id": 1940503557, "lat": 47.5786099, "lon": 7.5735705}, {"type": "node", "id": 1940503572, "lat": 47.5783584, "lon": 7.5723635}, {"type": "node", "id": 1940503585, "lat": 47.5783003, "lon": 7.5725679}, {"type": "node", "id": 1940503587, "lat": 47.5783494, "lon": 7.5730107}, {"type": "node", "id": 1940503601, "lat": 47.5785271, "lon": 7.5694767}, {"type": "node", "id": 1940503614, "lat": 47.5794536, "lon": 7.571863}, {"type": "node", "id": 1940503616, "lat": 47.5783802, "lon": 7.5726908}, {"type": "node", "id": 1940503633, "lat": 47.5784055, "lon": 7.5724896}, {"type": "node", "id": 1940503657, "lat": 47.5784849, "lon": 7.5693821}, {"type": "node", "id": 1940503658, "lat": 47.5784363, "lon": 7.5729456}, {"type": "node", "id": 1940503660, "lat": 47.5794232, "lon": 7.5718942}, {"type": "node", "id": 1940503664, "lat": 47.5782209, "lon": 7.5694989}, {"type": "node", "id": 1940503670, "lat": 47.5783196, "lon": 7.5727337}, {"type": "node", "id": 1940503675, "lat": 47.5794985, "lon": 7.571965}, {"type": "node", "id": 1940503687, "lat": 47.5783675, "lon": 7.5736242}, {"type": "node", "id": 1940503699, "lat": 47.5783784, "lon": 7.573761}, {"type": "node", "id": 1945168898, "lat": 47.5824229, "lon": 7.5656724}, {"type": "node", "id": 1945168915, "lat": 47.5823479, "lon": 7.566064}, {"type": "node", "id": 1945168916, "lat": 47.5823252, "lon": 7.565486}, {"type": "node", "id": 1945168917, "lat": 47.5822746, "lon": 7.5661445}, {"type": "node", "id": 1945168932, "lat": 47.5820891, "lon": 7.565769}, {"type": "node", "id": 1945202737, "lat": 47.5833631, "lon": 7.5655219}, {"type": "node", "id": 1945202745, "lat": 47.5834374, "lon": 7.5656895}, {"type": "node", "id": 1945202769, "lat": 47.5831207, "lon": 7.5655836}, {"type": "node", "id": 1945202791, "lat": 47.5832681, "lon": 7.5654387}, {"type": "node", "id": 1945202823, "lat": 47.5833233, "lon": 7.56555}, {"type": "node", "id": 1979445349, "lat": 47.5814319, "lon": 7.5758088}, {"type": "node", "id": 1979445357, "lat": 47.5814504, "lon": 7.5759656}, {"type": "node", "id": 1979445364, "lat": 47.5811249, "lon": 7.5760543}, {"type": "node", "id": 1979445366, "lat": 47.5811049, "lon": 7.575884}, {"type": "node", "id": 1979445386, "lat": 47.581222, "lon": 7.5758632}, {"type": "node", "id": 1979445394, "lat": 47.5810055, "lon": 7.576085}, {"type": "node", "id": 1979445398, "lat": 47.5812404, "lon": 7.57602}, {"type": "node", "id": 1979445400, "lat": 47.5809855, "lon": 7.5759147}, {"type": "node", "id": 2376370464, "lat": 47.5765959, "lon": 7.5654763}, {"type": "node", "id": 2376370470, "lat": 47.5764747, "lon": 7.5653127}, {"type": "node", "id": 2376370479, "lat": 47.5776501, "lon": 7.5643508}, {"type": "node", "id": 2376370482, "lat": 47.5777087, "lon": 7.5656909}, {"type": "node", "id": 2376370489, "lat": 47.5779096, "lon": 7.5647441}, {"type": "node", "id": 2376370491, "lat": 47.5767733, "lon": 7.5647226}, {"type": "node", "id": 2376370492, "lat": 47.5767624, "lon": 7.5657231}, {"type": "node", "id": 2376370496, "lat": 47.5778444, "lon": 7.5647414}, {"type": "node", "id": 2376370497, "lat": 47.5765905, "lon": 7.5649587}, {"type": "node", "id": 2376370500, "lat": 47.5764711, "lon": 7.5654763}, {"type": "node", "id": 2376370502, "lat": 47.5765869, "lon": 7.5651491}, {"type": "node", "id": 2376370522, "lat": 47.5774663, "lon": 7.5640628}, {"type": "node", "id": 2376370531, "lat": 47.5779584, "lon": 7.5648326}, {"type": "node", "id": 2376370534, "lat": 47.5779421, "lon": 7.5651679}, {"type": "node", "id": 2376370537, "lat": 47.5778209, "lon": 7.5640601}, {"type": "node", "id": 2376370548, "lat": 47.5777612, "lon": 7.5656587}, {"type": "node", "id": 2376375568, "lat": 47.5773342, "lon": 7.562652}, {"type": "node", "id": 2376375574, "lat": 47.5770303, "lon": 7.5633062}, {"type": "node", "id": 2376375575, "lat": 47.5768873, "lon": 7.562652}, {"type": "node", "id": 2376375578, "lat": 47.5771756, "lon": 7.5629599}, {"type": "node", "id": 2376375583, "lat": 47.5767128, "lon": 7.5629507}, {"type": "node", "id": 2376375584, "lat": 47.5771407, "lon": 7.5634699}, {"type": "node", "id": 2376375586, "lat": 47.5773686, "lon": 7.5631322}, {"type": "node", "id": 2376380350, "lat": 47.5812405, "lon": 7.5679037}, {"type": "node", "id": 2376380360, "lat": 47.581322, "lon": 7.5678206}, {"type": "node", "id": 2376380362, "lat": 47.5809511, "lon": 7.5669703}, {"type": "node", "id": 2376380364, "lat": 47.5808733, "lon": 7.5670401}, {"type": "node", "id": 2376380365, "lat": 47.580781, "lon": 7.5668282}, {"type": "node", "id": 2376380374, "lat": 47.5796266, "lon": 7.5657204}, {"type": "node", "id": 2376380380, "lat": 47.5794276, "lon": 7.565302}, {"type": "node", "id": 2376380382, "lat": 47.5796067, "lon": 7.5651679}, {"type": "node", "id": 2376380387, "lat": 47.5801599, "lon": 7.5660857}, {"type": "node", "id": 2376380390, "lat": 47.5797334, "lon": 7.5656668}, {"type": "node", "id": 2376380391, "lat": 47.5804581, "lon": 7.566711}, {"type": "node", "id": 2376380393, "lat": 47.5796393, "lon": 7.5657472}, {"type": "node", "id": 2376380398, "lat": 47.5794041, "lon": 7.5652859}, {"type": "node", "id": 2376380410, "lat": 47.5809366, "lon": 7.56715}, {"type": "node", "id": 2376380413, "lat": 47.5808968, "lon": 7.5671232}, {"type": "node", "id": 2376380414, "lat": 47.5806833, "lon": 7.5672868}, {"type": "node", "id": 2376380415, "lat": 47.5805566, "lon": 7.5670106}, {"type": "node", "id": 2376380416, "lat": 47.5801453, "lon": 7.5670035}, {"type": "node", "id": 2376380419, "lat": 47.580169, "lon": 7.5671199, "tags": {"barrier": "gate"}}, {"type": "node", "id": 2376380420, "lat": 47.5798428, "lon": 7.5662657}, {"type": "node", "id": 2376380422, "lat": 47.579699, "lon": 7.5654388}, {"type": "node", "id": 2376380424, "lat": 47.5792702, "lon": 7.5656078}, {"type": "node", "id": 2376380425, "lat": 47.5796664, "lon": 7.5654602}, {"type": "node", "id": 2376388447, "lat": 47.5830193, "lon": 7.5730694}, {"type": "node", "id": 2376388449, "lat": 47.5828071, "lon": 7.5732539}, {"type": "node", "id": 2376388457, "lat": 47.5829164, "lon": 7.5728901}, {"type": "node", "id": 2376388459, "lat": 47.5827413, "lon": 7.5730318}, {"type": "node", "id": 2464320815, "lat": 47.5753722, "lon": 7.5660143}, {"type": "node", "id": 2464320816, "lat": 47.5749478, "lon": 7.5663628}, {"type": "node", "id": 2464320818, "lat": 47.5747671, "lon": 7.5658918}, {"type": "node", "id": 2464320820, "lat": 47.5751913, "lon": 7.5655343}, {"type": "node", "id": 2464320827, "lat": 47.5753303, "lon": 7.5658965}, {"type": "node", "id": 2466017446, "lat": 47.5755835, "lon": 7.5735464}, {"type": "node", "id": 2466017449, "lat": 47.5756282, "lon": 7.5736789}, {"type": "node", "id": 2466017451, "lat": 47.5755787, "lon": 7.5738879}, {"type": "node", "id": 2466017453, "lat": 47.5756841, "lon": 7.5739393}, {"type": "node", "id": 2466017455, "lat": 47.5756491, "lon": 7.574092}, {"type": "node", "id": 2466017457, "lat": 47.575503, "lon": 7.5742047}, {"type": "node", "id": 2466017459, "lat": 47.5753945, "lon": 7.5741501}, {"type": "node", "id": 2466017461, "lat": 47.5751931, "lon": 7.5750375}, {"type": "node", "id": 2466017464, "lat": 47.5749794, "lon": 7.5745179}, {"type": "node", "id": 2466017466, "lat": 47.5748817, "lon": 7.5746272}, {"type": "node", "id": 2466017468, "lat": 47.5744617, "lon": 7.5749777}, {"type": "node", "id": 2466017470, "lat": 47.5743331, "lon": 7.5747027}, {"type": "node", "id": 2466017472, "lat": 47.5752479, "lon": 7.5738582}, {"type": "node", "id": 2466017483, "lat": 47.5750185, "lon": 7.5746556}, {"type": "node", "id": 2466017484, "lat": 47.5751063, "lon": 7.5748477}, {"type": "node", "id": 2466017501, "lat": 47.5764587, "lon": 7.5739899}, {"type": "node", "id": 2466017502, "lat": 47.5760507, "lon": 7.5737824}, {"type": "node", "id": 2466017503, "lat": 47.5761234, "lon": 7.5734681}, {"type": "node", "id": 2616036516, "lat": 47.5704406, "lon": 7.5829137}, {"type": "node", "id": 2616036517, "lat": 47.5703892, "lon": 7.5829491}, {"type": "node", "id": 2616036518, "lat": 47.5702173, "lon": 7.5829199}, {"type": "node", "id": 2616036519, "lat": 47.5702131, "lon": 7.5829703}, {"type": "node", "id": 2616036520, "lat": 47.5701994, "lon": 7.5829703}, {"type": "node", "id": 2616036521, "lat": 47.5701871, "lon": 7.5831694}, {"type": "node", "id": 2616036522, "lat": 47.5704373, "lon": 7.5832065}, {"type": "node", "id": 2616036523, "lat": 47.5704155, "lon": 7.5829309}, {"type": "node", "id": 2685205575, "lat": 47.5698727, "lon": 7.5829592}, {"type": "node", "id": 2685205578, "lat": 47.5698793, "lon": 7.5828602}, {"type": "node", "id": 2918944229, "lat": 47.5824009, "lon": 7.5774796}, {"type": "node", "id": 2918944234, "lat": 47.582402, "lon": 7.5769041}, {"type": "node", "id": 3391859978, "lat": 47.5811042, "lon": 7.5758047}, {"type": "node", "id": 3391859979, "lat": 47.5810547, "lon": 7.5758173}, {"type": "node", "id": 3391859980, "lat": 47.5810346, "lon": 7.5756439}, {"type": "node", "id": 3391859990, "lat": 47.5811708, "lon": 7.5736601}, {"type": "node", "id": 3391859991, "lat": 47.581102, "lon": 7.5736771}, {"type": "node", "id": 3391859992, "lat": 47.5810065, "lon": 7.5739262}, {"type": "node", "id": 3392455230, "lat": 47.5809756, "lon": 7.5750937}, {"type": "node", "id": 3392455233, "lat": 47.5809879, "lon": 7.5751993}, {"type": "node", "id": 3392455237, "lat": 47.5810623, "lon": 7.5750715}, {"type": "node", "id": 3392455239, "lat": 47.5810723, "lon": 7.5751764}, {"type": "node", "id": 3392462329, "lat": 47.5813664, "lon": 7.5710361}, {"type": "node", "id": 3392462331, "lat": 47.5814872, "lon": 7.5709215}, {"type": "node", "id": 3392462332, "lat": 47.58153, "lon": 7.5714149}, {"type": "node", "id": 3392462333, "lat": 47.5815685, "lon": 7.5716885}, {"type": "node", "id": 3392462334, "lat": 47.5815565, "lon": 7.570872}, {"type": "node", "id": 3392462335, "lat": 47.581659, "lon": 7.5716063}, {"type": "node", "id": 3392462336, "lat": 47.5816371, "lon": 7.5708}, {"type": "node", "id": 3392462338, "lat": 47.5816508, "lon": 7.5713003}, {"type": "node", "id": 3392462339, "lat": 47.5816521, "lon": 7.5718905}, {"type": "node", "id": 3392462341, "lat": 47.5817438, "lon": 7.5718072}, {"type": "node", "id": 3392462343, "lat": 47.5818417, "lon": 7.5712921}, {"type": "node", "id": 3392462344, "lat": 47.5822155, "lon": 7.571434}, {"type": "node", "id": 3392462345, "lat": 47.5822252, "lon": 7.5713342}, {"type": "node", "id": 3392462346, "lat": 47.5822403, "lon": 7.5714948}, {"type": "node", "id": 3392462347, "lat": 47.5822524, "lon": 7.5714009}, {"type": "node", "id": 3392462348, "lat": 47.5822772, "lon": 7.5714617}, {"type": "node", "id": 3392462350, "lat": 47.5823014, "lon": 7.571521}, {"type": "node", "id": 3392462351, "lat": 47.5823598, "lon": 7.5712134}, {"type": "node", "id": 3392462352, "lat": 47.5824361, "lon": 7.5714003}, {"type": "node", "id": 3392485390, "lat": 47.5795659, "lon": 7.5724229}, {"type": "node", "id": 3392485391, "lat": 47.5795796, "lon": 7.5723431}, {"type": "node", "id": 3392485392, "lat": 47.5796334, "lon": 7.5722735}, {"type": "node", "id": 3392485693, "lat": 47.5796608, "lon": 7.5723765}, {"type": "node", "id": 3392485694, "lat": 47.5796657, "lon": 7.5723475}, {"type": "node", "id": 3392485695, "lat": 47.5797527, "lon": 7.5721648}, {"type": "node", "id": 3392485696, "lat": 47.5797772, "lon": 7.572217}, {"type": "node", "id": 3392485697, "lat": 47.579786, "lon": 7.5723011}, {"type": "node", "id": 3392485698, "lat": 47.5798036, "lon": 7.5725461}, {"type": "node", "id": 3392485699, "lat": 47.5798051, "lon": 7.5725302}, {"type": "node", "id": 3392485700, "lat": 47.5800725, "lon": 7.5726309}, {"type": "node", "id": 3392485701, "lat": 47.5801126, "lon": 7.5724576}, {"type": "node", "id": 3392485702, "lat": 47.5801917, "lon": 7.5720556}, {"type": "node", "id": 3392485706, "lat": 47.5802697, "lon": 7.5719656}, {"type": "node", "id": 3392485707, "lat": 47.5803119, "lon": 7.5725882}, {"type": "node", "id": 3392485708, "lat": 47.580338, "lon": 7.5722573}, {"type": "node", "id": 3392485709, "lat": 47.5804725, "lon": 7.5726161}, {"type": "node", "id": 3392485710, "lat": 47.5804987, "lon": 7.5722852}, {"type": "node", "id": 3392485711, "lat": 47.5804855, "lon": 7.5721449}, {"type": "node", "id": 3392485712, "lat": 47.5805249, "lon": 7.5720374}, {"type": "node", "id": 3392485713, "lat": 47.5807226, "lon": 7.5721745}, {"type": "node", "id": 3392485714, "lat": 47.5807635, "lon": 7.5720661}, {"type": "node", "id": 3392485715, "lat": 47.5809262, "lon": 7.5721927}, {"type": "node", "id": 3392485716, "lat": 47.5809585, "lon": 7.5720948}, {"type": "node", "id": 3769058726, "lat": 47.5801124, "lon": 7.5660142}, {"type": "node", "id": 3770111747, "lat": 47.5794489, "lon": 7.565475, "tags": {"addr:housenumber": "2", "source": "Direction G\u00e9n\u00e9rale des Finances Publiques - cadastre. Mise \u00e0 jour : 2015"}}, {"type": "node", "id": 3793321251, "lat": 47.5811234, "lon": 7.5737912}, {"type": "node", "id": 3793321252, "lat": 47.58174, "lon": 7.5712979}, {"type": "node", "id": 4128465236, "lat": 47.5752936, "lon": 7.5745901}, {"type": "node", "id": 4128465238, "lat": 47.5753521, "lon": 7.5743351}, {"type": "node", "id": 4128465244, "lat": 47.5745467, "lon": 7.5749741}, {"type": "node", "id": 4173391638, "lat": 47.5736266, "lon": 7.5637373, "tags": {"access": "customers", "amenity": "parking", "fee": "no", "name": "Airport Hotel", "parking": "underground", "supervised": "no"}}, {"type": "node", "id": 4217355225, "lat": 47.5778549, "lon": 7.5694432}, {"type": "node", "id": 4217355226, "lat": 47.5779522, "lon": 7.5694694}, {"type": "node", "id": 4217355227, "lat": 47.5778933, "lon": 7.5698248}, {"type": "node", "id": 4217355228, "lat": 47.5778205, "lon": 7.5698093}, {"type": "node", "id": 4217355229, "lat": 47.5779662, "lon": 7.5691496}, {"type": "node", "id": 4217355230, "lat": 47.5779698, "lon": 7.5692762}, {"type": "node", "id": 4217355231, "lat": 47.5778729, "lon": 7.5692795}, {"type": "node", "id": 4217355233, "lat": 47.5779204, "lon": 7.5702977}, {"type": "node", "id": 4217355234, "lat": 47.5779444, "lon": 7.5704987}, {"type": "node", "id": 4217355235, "lat": 47.5778651, "lon": 7.5705195}, {"type": "node", "id": 4217355236, "lat": 47.5778411, "lon": 7.5703185}, {"type": "node", "id": 4217355237, "lat": 47.577827, "lon": 7.569706}, {"type": "node", "id": 4217355245, "lat": 47.578461, "lon": 7.5680081}, {"type": "node", "id": 4217355246, "lat": 47.5785225, "lon": 7.5680952}, {"type": "node", "id": 4217355247, "lat": 47.5782565, "lon": 7.5683004}, {"type": "node", "id": 4217355248, "lat": 47.5782077, "lon": 7.5682065}, {"type": "node", "id": 4217355255, "lat": 47.5784621, "lon": 7.5708814}, {"type": "node", "id": 4217355256, "lat": 47.5784856, "lon": 7.5709414}, {"type": "node", "id": 4217355257, "lat": 47.5783192, "lon": 7.571097}, {"type": "node", "id": 4217355258, "lat": 47.5782938, "lon": 7.5710376}, {"type": "node", "id": 4217355275, "lat": 47.5776609, "lon": 7.5737538}, {"type": "node", "id": 4217355276, "lat": 47.5775126, "lon": 7.5729491}, {"type": "node", "id": 4217355277, "lat": 47.5769227, "lon": 7.5731959}, {"type": "node", "id": 4217355278, "lat": 47.5768865, "lon": 7.5730778}, {"type": "node", "id": 4217355279, "lat": 47.5767415, "lon": 7.5730069}, {"type": "node", "id": 4217355280, "lat": 47.5764631, "lon": 7.5750734}, {"type": "node", "id": 4217355281, "lat": 47.5764341, "lon": 7.5754972}, {"type": "node", "id": 4217355282, "lat": 47.5765934, "lon": 7.5756528}, {"type": "node", "id": 4217355283, "lat": 47.576825, "lon": 7.5764896}, {"type": "node", "id": 4217355284, "lat": 47.5767454, "lon": 7.5766988}, {"type": "node", "id": 4217355285, "lat": 47.576977, "lon": 7.57701}, {"type": "node", "id": 4217355286, "lat": 47.5783738, "lon": 7.5773587}, {"type": "node", "id": 4217355287, "lat": 47.5786353, "lon": 7.5745531}, {"type": "node", "id": 4499158180, "lat": 47.5765136, "lon": 7.5737529}, {"type": "node", "id": 4890221739, "lat": 47.5804083, "lon": 7.5720046}, {"type": "node", "id": 4890221758, "lat": 47.5803908, "lon": 7.5726019}, {"type": "node", "id": 4890221760, "lat": 47.5803433, "lon": 7.5725937}, {"type": "node", "id": 4890221779, "lat": 47.5799245, "lon": 7.5723675}, {"type": "node", "id": 4890221781, "lat": 47.5797713, "lon": 7.5722044}, {"type": "node", "id": 5138626764, "lat": 47.5797425, "lon": 7.5697473}, {"type": "node", "id": 5138626765, "lat": 47.5797082, "lon": 7.5697875}, {"type": "node", "id": 5138626766, "lat": 47.5798384, "lon": 7.570096}, {"type": "node", "id": 5138626767, "lat": 47.5797579, "lon": 7.5701711}, {"type": "node", "id": 5138626768, "lat": 47.5797073, "lon": 7.5701268}, {"type": "node", "id": 5138626769, "lat": 47.579491, "lon": 7.5703306}, {"type": "node", "id": 5138626770, "lat": 47.5794901, "lon": 7.5704192}, {"type": "node", "id": 5138626771, "lat": 47.5794349, "lon": 7.5704782}, {"type": "node", "id": 5138626772, "lat": 47.5794141, "lon": 7.5704808}, {"type": "node", "id": 5138626773, "lat": 47.579396, "lon": 7.5704741}, {"type": "node", "id": 5138626774, "lat": 47.5792821, "lon": 7.5702059}, {"type": "node", "id": 5138626775, "lat": 47.5792296, "lon": 7.5702126}, {"type": "node", "id": 5138626779, "lat": 47.5799108, "lon": 7.5700892}, {"type": "node", "id": 5138626780, "lat": 47.5793707, "lon": 7.5705962}, {"type": "node", "id": 5138626783, "lat": 47.5797712, "lon": 7.5697331}, {"type": "node", "id": 5138626784, "lat": 47.5792104, "lon": 7.5702336}, {"type": "node", "id": 5138653435, "lat": 47.5811725, "lon": 7.567735}, {"type": "node", "id": 5159878474, "lat": 47.5794476, "lon": 7.5786081}, {"type": "node", "id": 5159878518, "lat": 47.5783999, "lon": 7.5777659}, {"type": "node", "id": 5159878519, "lat": 47.5783321, "lon": 7.5783238}, {"type": "node", "id": 5159878625, "lat": 47.5795543, "lon": 7.5780636}, {"type": "node", "id": 5159878680, "lat": 47.5794982, "lon": 7.5785517}, {"type": "node", "id": 5159878701, "lat": 47.5794548, "lon": 7.5785397}, {"type": "node", "id": 5309079621, "lat": 47.5749877, "lon": 7.5866554}, {"type": "node", "id": 5309079622, "lat": 47.5750127, "lon": 7.5869239}, {"type": "node", "id": 5309079623, "lat": 47.5744661, "lon": 7.5870439}, {"type": "node", "id": 5309079624, "lat": 47.5744311, "lon": 7.5867343}, {"type": "node", "id": 5309079625, "lat": 47.5746171, "lon": 7.5870655}, {"type": "node", "id": 5309079626, "lat": 47.5747749, "lon": 7.5870613}, {"type": "node", "id": 5309079627, "lat": 47.5749714, "lon": 7.5870458}, {"type": "node", "id": 5309079628, "lat": 47.5749665, "lon": 7.5869896}, {"type": "node", "id": 5309079629, "lat": 47.5749609, "lon": 7.5869301}, {"type": "node", "id": 5640481860, "lat": 47.5828886, "lon": 7.5682685}, {"type": "node", "id": 5640481861, "lat": 47.5828026, "lon": 7.5683302}, {"type": "node", "id": 5640481862, "lat": 47.5827284, "lon": 7.5681183}, {"type": "node", "id": 5640481863, "lat": 47.5826877, "lon": 7.5681491}, {"type": "node", "id": 5640481864, "lat": 47.5826687, "lon": 7.5680915}, {"type": "node", "id": 5640481865, "lat": 47.5825374, "lon": 7.5681827}, {"type": "node", "id": 5640481866, "lat": 47.5825537, "lon": 7.568239}, {"type": "node", "id": 5640481867, "lat": 47.5825057, "lon": 7.5682524}, {"type": "node", "id": 5640481868, "lat": 47.582541, "lon": 7.5685756}, {"type": "node", "id": 5640481869, "lat": 47.5825871, "lon": 7.5685635}, {"type": "node", "id": 5640481870, "lat": 47.5826315, "lon": 7.5685367}, {"type": "node", "id": 5640481871, "lat": 47.5826088, "lon": 7.5684603}, {"type": "node", "id": 5640481872, "lat": 47.5827292, "lon": 7.5683825}, {"type": "node", "id": 5640481873, "lat": 47.5827545, "lon": 7.5684643}, {"type": "node", "id": 5640481874, "lat": 47.5829155, "lon": 7.5683503}, {"type": "node", "id": 5759453750, "lat": 47.5706433, "lon": 7.5665426, "tags": {"amenity": "parking", "parking": "street_side"}}, {"type": "node", "id": 6180499282, "lat": 47.5748266, "lon": 7.574223}, {"type": "node", "id": 6191236690, "lat": 47.5803006, "lon": 7.5678773}, {"type": "node", "id": 6191236725, "lat": 47.5765314, "lon": 7.5736756}, {"type": "node", "id": 6191236728, "lat": 47.5762547, "lon": 7.5748125}, {"type": "node", "id": 6372064548, "lat": 47.5750537, "lon": 7.5745998}, {"type": "node", "id": 6372064549, "lat": 47.5750121, "lon": 7.5745804}, {"type": "node", "id": 6372064550, "lat": 47.5750379, "lon": 7.5745334}, {"type": "node", "id": 6402424824, "lat": 47.5758607, "lon": 7.563271}, {"type": "node", "id": 6576981229, "lat": 47.5827737, "lon": 7.5731619}, {"type": "node", "id": 6621885481, "lat": 47.5723612, "lon": 7.5626917}, {"type": "node", "id": 6621885482, "lat": 47.5719153, "lon": 7.5633385}, {"type": "node", "id": 6621885483, "lat": 47.5719027, "lon": 7.5632194}, {"type": "node", "id": 6621885484, "lat": 47.5718728, "lon": 7.5631144}, {"type": "node", "id": 6621914385, "lat": 47.571772, "lon": 7.5629719}, {"type": "node", "id": 6621914386, "lat": 47.5715546, "lon": 7.5626404}, {"type": "node", "id": 6621914387, "lat": 47.5719847, "lon": 7.5620356}, {"type": "node", "id": 6627800178, "lat": 47.5804342, "lon": 7.5721361}, {"type": "node", "id": 6627801408, "lat": 47.5793078, "lon": 7.5655174}, {"type": "node", "id": 6627801413, "lat": 47.5793861, "lon": 7.5653293, "tags": {"direction": "backward", "highway": "stop"}}, {"type": "node", "id": 6627808530, "lat": 47.5778699, "lon": 7.5685954}, {"type": "node", "id": 6627808531, "lat": 47.5778761, "lon": 7.5687338}, {"type": "node", "id": 6627808532, "lat": 47.5779508, "lon": 7.5687264}, {"type": "node", "id": 6627808533, "lat": 47.5779446, "lon": 7.568588}, {"type": "node", "id": 6628627556, "lat": 47.5829502, "lon": 7.5731662}, {"type": "node", "id": 7523152167, "lat": 47.5820921, "lon": 7.5886251}, {"type": "node", "id": 7523152168, "lat": 47.5820401, "lon": 7.5885969}, {"type": "node", "id": 7523152169, "lat": 47.5820089, "lon": 7.5887076}, {"type": "node", "id": 7523152170, "lat": 47.5817353, "lon": 7.5884943}, {"type": "node", "id": 7523152171, "lat": 47.5817932, "lon": 7.5881664}, {"type": "node", "id": 7523152172, "lat": 47.5822025, "lon": 7.58809}, {"type": "node", "id": 8072598504, "lat": 47.5783293, "lon": 7.5773476, "tags": {"barrier": "gate"}}, {"type": "node", "id": 8427811559, "lat": 47.5722961, "lon": 7.5625783}, {"type": "node", "id": 8427811566, "lat": 47.5722768, "lon": 7.5625447}, {"type": "node", "id": 8427811585, "lat": 47.5744858, "lon": 7.5867265}, {"type": "node", "id": 8589530624, "lat": 47.5699274, "lon": 7.5828672}, {"type": "node", "id": 8589530625, "lat": 47.5697045, "lon": 7.5828421}, {"type": "node", "id": 8589530626, "lat": 47.5697162, "lon": 7.5828421}, {"type": "node", "id": 8589530627, "lat": 47.5697151, "lon": 7.5827247}, {"type": "node", "id": 8589530628, "lat": 47.5698886, "lon": 7.5827455}, {"type": "node", "id": 8589530629, "lat": 47.5697343, "lon": 7.5829547}, {"type": "node", "id": 8589530630, "lat": 47.5697354, "lon": 7.5829391}, {"type": "node", "id": 8589530631, "lat": 47.5697001, "lon": 7.5829497}, {"type": "node", "id": 8851515158, "lat": 47.5749729, "lon": 7.5869277}, {"type": "node", "id": 9901987683, "lat": 47.5821213, "lon": 7.5811853}, {"type": "node", "id": 9901987684, "lat": 47.5820588, "lon": 7.5819078}, {"type": "node", "id": 9901987685, "lat": 47.5809387, "lon": 7.5817335}, {"type": "node", "id": 9901987686, "lat": 47.5809877, "lon": 7.5809993}, {"type": "node", "id": 9929220692, "lat": 47.5820866, "lon": 7.5815952}, {"type": "node", "id": 9929220693, "lat": 47.5820742, "lon": 7.5817311}, {"type": "node", "id": 10967894005, "lat": 47.5784148, "lon": 7.5709253, "tags": {"addr:housenumber": "90"}}, {"type": "node", "id": 11384407287, "lat": 47.5811407, "lon": 7.5884363}, {"type": "node", "id": 11384407288, "lat": 47.5811348, "lon": 7.588469}, {"type": "node", "id": 11384407289, "lat": 47.5810265, "lon": 7.5884305}, {"type": "node", "id": 11384407290, "lat": 47.5809717, "lon": 7.5884129}, {"type": "node", "id": 11384407291, "lat": 47.5809162, "lon": 7.5883989}, {"type": "node", "id": 11384407292, "lat": 47.5808579, "lon": 7.5883884}, {"type": "node", "id": 11384407293, "lat": 47.5807469, "lon": 7.5883785}, {"type": "node", "id": 11384407294, "lat": 47.5807485, "lon": 7.5883446}, {"type": "node", "id": 11384407295, "lat": 47.5808604, "lon": 7.5883518}, {"type": "node", "id": 11384407296, "lat": 47.5809194, "lon": 7.5883668}, {"type": "node", "id": 11384407297, "lat": 47.5810332, "lon": 7.5883966}, {"type": "node", "id": 11384407298, "lat": 47.581097, "lon": 7.5884141}, {"type": "node", "id": 11780020145, "lat": 47.5823614, "lon": 7.5770301}, {"type": "node", "id": 11780020146, "lat": 47.5824782, "lon": 7.5771613}, {"type": "node", "id": 11780020147, "lat": 47.5823853, "lon": 7.5774744}, {"type": "node", "id": 11780020148, "lat": 47.5823022, "lon": 7.5774196}, {"type": "node", "id": 11780020149, "lat": 47.582329, "lon": 7.5773106}, {"type": "node", "id": 11780020150, "lat": 47.582289, "lon": 7.5772813}, {"type": "node", "id": 11780020151, "lat": 47.5823611, "lon": 7.5770485}, {"type": "node", "id": 11780020152, "lat": 47.5824267, "lon": 7.5770915}, {"type": "node", "id": 11813359116, "lat": 47.5834955, "lon": 7.5772437}, {"type": "node", "id": 11813359117, "lat": 47.5831983, "lon": 7.5781374}, {"type": "node", "id": 11813359118, "lat": 47.5832365, "lon": 7.578048}, {"type": "node", "id": 11813400116, "lat": 47.5780862, "lon": 7.5727874}, {"type": "node", "id": 11813400117, "lat": 47.5778558, "lon": 7.5729207}, {"type": "node", "id": 11813400118, "lat": 47.5776325, "lon": 7.5729621}, {"type": "node", "id": 11813400119, "lat": 47.5777679, "lon": 7.5736515}, {"type": "node", "id": 11813400120, "lat": 47.5779064, "lon": 7.5735979}, {"type": "node", "id": 11813400121, "lat": 47.5779188, "lon": 7.5735029}, {"type": "node", "id": 11813400122, "lat": 47.5778444, "lon": 7.5731398}, {"type": "node", "id": 11813400123, "lat": 47.5779746, "lon": 7.5731107}, {"type": "node", "id": 11813400124, "lat": 47.5781503, "lon": 7.5730372}, {"type": "node", "id": 11880919499, "lat": 47.5704232, "lon": 7.5753819}, {"type": "node", "id": 12116745509, "lat": 47.5661345, "lon": 7.5731943}, {"type": "node", "id": 12116745510, "lat": 47.5663066, "lon": 7.5729492}, {"type": "node", "id": 12116745511, "lat": 47.5662798, "lon": 7.5729079}, {"type": "node", "id": 12118356089, "lat": 47.5708404, "lon": 7.5730197}, {"type": "node", "id": 12118356090, "lat": 47.5708803, "lon": 7.573138}, {"type": "node", "id": 12118356091, "lat": 47.5708966, "lon": 7.573126}, {"type": "node", "id": 12118356092, "lat": 47.5708566, "lon": 7.5730077}, {"type": "node", "id": 12118356093, "lat": 47.5709831, "lon": 7.5739678}, {"type": "node", "id": 12118356094, "lat": 47.5709913, "lon": 7.5741658}, {"type": "node", "id": 12118356095, "lat": 47.5710108, "lon": 7.574164}, {"type": "node", "id": 12118356096, "lat": 47.5710026, "lon": 7.573966}, {"type": "node", "id": 12118356097, "lat": 47.5710893, "lon": 7.5739513}, {"type": "node", "id": 12118356098, "lat": 47.5710975, "lon": 7.5741494}, {"type": "node", "id": 12118356099, "lat": 47.571117, "lon": 7.5741476}, {"type": "node", "id": 12118356100, "lat": 47.5711088, "lon": 7.5739496}, {"type": "node", "id": 12118384801, "lat": 47.5710246, "lon": 7.5733084}, {"type": "node", "id": 12118384802, "lat": 47.5710493, "lon": 7.5735034}, {"type": "node", "id": 12118384803, "lat": 47.5710685, "lon": 7.5734981}, {"type": "node", "id": 12118384804, "lat": 47.5710438, "lon": 7.5733031}, {"type": "node", "id": 12118384805, "lat": 47.5709251, "lon": 7.5729128}, {"type": "node", "id": 12118384806, "lat": 47.5709955, "lon": 7.5731518}, {"type": "node", "id": 12118384807, "lat": 47.570996, "lon": 7.5730806}, {"type": "node", "id": 12118384808, "lat": 47.5709429, "lon": 7.5729008}, {"type": "node", "id": 12118384809, "lat": 47.5709807, "lon": 7.5730927}, {"type": "node", "id": 12118384810, "lat": 47.5710114, "lon": 7.5731441}, {"type": "node", "id": 12118384811, "lat": 47.5710657, "lon": 7.5736424}, {"type": "node", "id": 12118384812, "lat": 47.5710729, "lon": 7.5737159}, {"type": "node", "id": 12118384813, "lat": 47.5710921, "lon": 7.5737118}, {"type": "node", "id": 12118384814, "lat": 47.5710849, "lon": 7.5736383}, {"type": "node", "id": 12118384815, "lat": 47.5709345, "lon": 7.5733203}, {"type": "node", "id": 12118384816, "lat": 47.5709565, "lon": 7.5734642}, {"type": "node", "id": 12118384817, "lat": 47.5709388, "lon": 7.5734702}, {"type": "node", "id": 12118384818, "lat": 47.5709168, "lon": 7.5733263}, {"type": "node", "id": 12118384824, "lat": 47.5704144, "lon": 7.5753599}, {"type": "node", "id": 12118384825, "lat": 47.5705455, "lon": 7.575275}, {"type": "node", "id": 12118384826, "lat": 47.5705368, "lon": 7.575253}, {"type": "node", "id": 12118384827, "lat": 47.5702039, "lon": 7.5755761}, {"type": "node", "id": 12118384828, "lat": 47.569791, "lon": 7.5759424}, {"type": "node", "id": 12118384829, "lat": 47.5697818, "lon": 7.5759196}, {"type": "node", "id": 12118384830, "lat": 47.5701947, "lon": 7.5755535}, {"type": "node", "id": 12118384848, "lat": 47.5697649, "lon": 7.5761525}, {"type": "node", "id": 12118384849, "lat": 47.5699156, "lon": 7.5764474}, {"type": "node", "id": 12118384850, "lat": 47.5699298, "lon": 7.5764315}, {"type": "node", "id": 12118384851, "lat": 47.5697791, "lon": 7.5761365}, {"type": "node", "id": 12118384852, "lat": 47.5697136, "lon": 7.5762124}, {"type": "node", "id": 12118384853, "lat": 47.5699255, "lon": 7.5766204}, {"type": "node", "id": 12118384854, "lat": 47.5699389, "lon": 7.5766052}, {"type": "node", "id": 12118384855, "lat": 47.5697271, "lon": 7.5761971}, {"type": "node", "id": 12118384856, "lat": 47.5699488, "lon": 7.5765135}, {"type": "node", "id": 12118384857, "lat": 47.5700018, "lon": 7.5766153}, {"type": "node", "id": 12118384858, "lat": 47.5700163, "lon": 7.5765988}, {"type": "node", "id": 12118384859, "lat": 47.5699632, "lon": 7.576497}, {"type": "node", "id": 12118384860, "lat": 47.5699573, "lon": 7.5766856}, {"type": "node", "id": 12118384861, "lat": 47.5699848, "lon": 7.5767374}, {"type": "node", "id": 12118384862, "lat": 47.5699976, "lon": 7.5767224}, {"type": "node", "id": 12118384863, "lat": 47.5699701, "lon": 7.5766706}, {"type": "node", "id": 12118384864, "lat": 47.57009, "lon": 7.5767896}, {"type": "node", "id": 12118384865, "lat": 47.5702887, "lon": 7.5771804}, {"type": "node", "id": 12118384866, "lat": 47.5703042, "lon": 7.5771631}, {"type": "node", "id": 12118384867, "lat": 47.5701055, "lon": 7.5767723}, {"type": "node", "id": 12118384868, "lat": 47.5701842, "lon": 7.5771285}, {"type": "node", "id": 12118384869, "lat": 47.5702434, "lon": 7.5772435}, {"type": "node", "id": 12118384870, "lat": 47.5702575, "lon": 7.5772276}, {"type": "node", "id": 12118384871, "lat": 47.5701983, "lon": 7.5771126}, {"type": "node", "id": 12118384872, "lat": 47.5698902, "lon": 7.5778159}, {"type": "node", "id": 12118384873, "lat": 47.5699012, "lon": 7.5778378}, {"type": "node", "id": 12118384876, "lat": 47.5697519, "lon": 7.5779684}, {"type": "node", "id": 12118384877, "lat": 47.5697629, "lon": 7.5779903}, {"type": "node", "id": 12230151687, "lat": 47.5797564, "lon": 7.5729625}, {"type": "node", "id": 12230151688, "lat": 47.57956, "lon": 7.5728873}, {"type": "node", "id": 12230151689, "lat": 47.5795475, "lon": 7.5729592}, {"type": "node", "id": 12230151690, "lat": 47.5797438, "lon": 7.5730345}, {"type": "node", "id": 12230151692, "lat": 47.5796351, "lon": 7.5729928}, {"type": "node", "id": 12474247785, "lat": 47.580485, "lon": 7.5636216}, {"type": "node", "id": 12474247786, "lat": 47.5804964, "lon": 7.5636459}, {"type": "node", "id": 12474247787, "lat": 47.5805131, "lon": 7.5636287}, {"type": "node", "id": 12474247788, "lat": 47.5805556, "lon": 7.5637194}, {"type": "node", "id": 12474247789, "lat": 47.5804326, "lon": 7.563846}, {"type": "node", "id": 12474247790, "lat": 47.5803787, "lon": 7.563731}, {"type": "node", "id": 12843796396, "lat": 47.5755576, "lon": 7.5881133}, {"type": "node", "id": 12843796397, "lat": 47.5755172, "lon": 7.588117}, {"type": "node", "id": 12843796398, "lat": 47.5755096, "lon": 7.5881226}, {"type": "node", "id": 12843796399, "lat": 47.5754478, "lon": 7.5883244}, {"type": "node", "id": 12843796400, "lat": 47.5754872, "lon": 7.588345}, {"type": "node", "id": 12843833701, "lat": 47.5754644, "lon": 7.5884232}, {"type": "node", "id": 12843833702, "lat": 47.575497, "lon": 7.5884445}, {"type": "node", "id": 12843833703, "lat": 47.5755204, "lon": 7.5883659}, {"type": "node", "id": 12843833704, "lat": 47.5755457, "lon": 7.5884191}, {"type": "node", "id": 12843833705, "lat": 47.575564, "lon": 7.5883988}, {"type": "node", "id": 12843833706, "lat": 47.5755731, "lon": 7.5884941}, {"type": "node", "id": 12843833707, "lat": 47.5756083, "lon": 7.5885179}, {"type": "node", "id": 12843833708, "lat": 47.5756307, "lon": 7.58844}, {"type": "node", "id": 12843833709, "lat": 47.5756825, "lon": 7.5884337}, {"type": "node", "id": 12843833710, "lat": 47.5757785, "lon": 7.5880698}, {"type": "node", "id": 12843833711, "lat": 47.5757434, "lon": 7.5880737}, {"type": "node", "id": 12843833712, "lat": 47.575749, "lon": 7.5880533}, {"type": "node", "id": 12843833713, "lat": 47.575755, "lon": 7.5880335}, {"type": "node", "id": 12843833714, "lat": 47.57576, "lon": 7.5880154}, {"type": "node", "id": 12843833715, "lat": 47.5757651, "lon": 7.5880051}, {"type": "node", "id": 12843833716, "lat": 47.5757794, "lon": 7.5879947}, {"type": "node", "id": 12843833717, "lat": 47.5757865, "lon": 7.5879969}, {"type": "node", "id": 12843833718, "lat": 47.5757859, "lon": 7.5880561}, {"type": "node", "id": 12843833719, "lat": 47.5758682, "lon": 7.5880654}, {"type": "node", "id": 12843833720, "lat": 47.5758717, "lon": 7.5880099}, {"type": "node", "id": 12843833721, "lat": 47.5758997, "lon": 7.5880046}, {"type": "node", "id": 12843833722, "lat": 47.5759201, "lon": 7.5879622}, {"type": "node", "id": 12843833723, "lat": 47.5759199, "lon": 7.5879325}, {"type": "node", "id": 12843833724, "lat": 47.5759111, "lon": 7.5879301}, {"type": "node", "id": 12843833725, "lat": 47.5759153, "lon": 7.5878702}, {"type": "node", "id": 12843833726, "lat": 47.5756028, "lon": 7.587831}, {"type": "node", "id": 12843833727, "lat": 47.5755996, "lon": 7.5878907}, {"type": "node", "id": 12843833728, "lat": 47.575594, "lon": 7.5879661}, {"type": "node", "id": 12843833729, "lat": 47.5755922, "lon": 7.587972}, {"type": "node", "id": 12843833730, "lat": 47.5755882, "lon": 7.5879741}, {"type": "node", "id": 12843833731, "lat": 47.5755816, "lon": 7.5879726}, {"type": "node", "id": 12843833732, "lat": 47.5755846, "lon": 7.5879141}, {"type": "node", "id": 12843833733, "lat": 47.5753183, "lon": 7.5878732}, {"type": "node", "id": 12843833734, "lat": 47.5753145, "lon": 7.587937}, {"type": "node", "id": 12843833735, "lat": 47.5753029, "lon": 7.5879349}, {"type": "node", "id": 12843833736, "lat": 47.5752977, "lon": 7.5880138}, {"type": "node", "id": 12843833737, "lat": 47.5753097, "lon": 7.588015}, {"type": "node", "id": 12843833738, "lat": 47.5753065, "lon": 7.5880788}, {"type": "node", "id": 12843833739, "lat": 47.5755321, "lon": 7.5881076}, {"type": "node", "id": 12843833740, "lat": 47.5755353, "lon": 7.5880581}, {"type": "node", "id": 12843833741, "lat": 47.5755383, "lon": 7.5880521}, {"type": "node", "id": 12843833742, "lat": 47.5755447, "lon": 7.5880521}, {"type": "node", "id": 12843833743, "lat": 47.5755524, "lon": 7.5880572}, {"type": "node", "id": 12843833744, "lat": 47.5755582, "lon": 7.5880684}, {"type": "node", "id": 12843833745, "lat": 47.5755614, "lon": 7.5880827}, {"type": "node", "id": 12843833746, "lat": 47.575561, "lon": 7.5880996}, {"type": "node", "id": 12843833747, "lat": 47.5754473, "lon": 7.5883493}, {"type": "node", "id": 12843833748, "lat": 47.5755735, "lon": 7.5883646}, {"type": "node", "id": 12843833749, "lat": 47.575555, "lon": 7.5883839}, {"type": "node", "id": 12843833750, "lat": 47.5755986, "lon": 7.5884179}, {"type": "node", "id": 12843833751, "lat": 47.5755915, "lon": 7.588506}, {"type": "node", "id": 12843833752, "lat": 47.5754808, "lon": 7.5884339}, {"type": "node", "id": 12843833753, "lat": 47.5757813, "lon": 7.5881055}, {"type": "node", "id": 12843833754, "lat": 47.5757896, "lon": 7.5880067}, {"type": "node", "id": 12843833755, "lat": 47.5755801, "lon": 7.5881683}, {"type": "node", "id": 12843833756, "lat": 47.5756124, "lon": 7.5882336}, {"type": "node", "id": 12843833757, "lat": 47.5755964, "lon": 7.5882523}, {"type": "node", "id": 12843833758, "lat": 47.5755706, "lon": 7.5882008}, {"type": "node", "id": 12843833759, "lat": 47.5756657, "lon": 7.5880211}, {"type": "node", "id": 12843833760, "lat": 47.5756723, "lon": 7.5880361}, {"type": "node", "id": 12843833761, "lat": 47.5756559, "lon": 7.5880537}, {"type": "node", "id": 12843833762, "lat": 47.5756304, "lon": 7.5880033}, {"type": "node", "id": 12843833763, "lat": 47.575634, "lon": 7.5879947}, {"type": "node", "id": 12843833764, "lat": 47.5756384, "lon": 7.5879883}, {"type": "node", "id": 12843833765, "lat": 47.5756441, "lon": 7.5879828}, {"type": "node", "id": 12843833766, "lat": 47.5756507, "lon": 7.5879804}, {"type": "node", "id": 12843833767, "lat": 47.575659, "lon": 7.5879791}, {"type": "node", "id": 12843833768, "lat": 47.5756853, "lon": 7.5879831}, {"type": "node", "id": 12843833769, "lat": 47.5756926, "lon": 7.5879866}, {"type": "node", "id": 12843833770, "lat": 47.5756993, "lon": 7.5879943}, {"type": "node", "id": 12843833771, "lat": 47.5757048, "lon": 7.5880029}, {"type": "node", "id": 12843833772, "lat": 47.5757083, "lon": 7.5880114}, {"type": "node", "id": 12843833773, "lat": 47.5757105, "lon": 7.588022}, {"type": "node", "id": 12843833774, "lat": 47.5757116, "lon": 7.5880319}, {"type": "node", "id": 12843833775, "lat": 47.5757108, "lon": 7.588042}, {"type": "node", "id": 12843833776, "lat": 47.5757091, "lon": 7.5880546}, {"type": "node", "id": 12843833777, "lat": 47.5756832, "lon": 7.5880024}, {"type": "node", "id": 12844080716, "lat": 47.5690261, "lon": 7.5863768}, {"type": "node", "id": 12844080717, "lat": 47.5690256, "lon": 7.5864099}, {"type": "node", "id": 12844080718, "lat": 47.5689705, "lon": 7.5864081}, {"type": "node", "id": 12844080719, "lat": 47.568971, "lon": 7.586375}, {"type": "node", "id": 12890332091, "lat": 47.5766935, "lon": 7.5617978}, {"type": "node", "id": 12890332092, "lat": 47.5767356, "lon": 7.561938}, {"type": "node", "id": 12890332093, "lat": 47.5767633, "lon": 7.56197}, {"type": "node", "id": 12890332094, "lat": 47.5765578, "lon": 7.5621787}, {"type": "node", "id": 12890332095, "lat": 47.5765085, "lon": 7.5622122}, {"type": "node", "id": 12890332096, "lat": 47.5764375, "lon": 7.562197}, {"type": "node", "id": 12890332097, "lat": 47.5763861, "lon": 7.5621559}, {"type": "node", "id": 12890332098, "lat": 47.5763461, "lon": 7.5620721}, {"type": "node", "id": 12890332099, "lat": 47.576345, "lon": 7.562005}, {"type": "node", "id": 12890332100, "lat": 47.5763574, "lon": 7.5619212}, {"type": "node", "id": 12890337701, "lat": 47.5764077, "lon": 7.5618557}, {"type": "node", "id": 12890337702, "lat": 47.5764622, "lon": 7.5618176}, {"type": "node", "id": 12890337703, "lat": 47.5765331, "lon": 7.5617978}, {"type": "node", "id": 12918045895, "lat": 47.5697461, "lon": 7.5711616}, {"type": "node", "id": 12918045896, "lat": 47.5697192, "lon": 7.5712179}, {"type": "node", "id": 12918045897, "lat": 47.5699, "lon": 7.5714081}, {"type": "node", "id": 12918045898, "lat": 47.569927, "lon": 7.5713517}, {"type": "node", "id": 12918045899, "lat": 47.5698274, "lon": 7.5715418}, {"type": "node", "id": 12918045900, "lat": 47.5698577, "lon": 7.5715778}, {"type": "node", "id": 12918062101, "lat": 47.5700093, "lon": 7.5715013}, {"type": "node", "id": 12918062102, "lat": 47.5699698, "lon": 7.5714593}, {"type": "way", "id": 28148630, "nodes": [309169828, 309169830, 309169832, 309169834, 309169828], "tags": {"amenity": "parking", "parking": "surface"}}, {"type": "way", "id": 31926465, "nodes": [357561966, 357561969, 6191236690, 357561972, 1637902901, 357561974, 2376380419, 357561966], "tags": {"amenity": "parking", "parking": "surface"}}, {"type": "way", "id": 103009733, "nodes": [1189453601, 1189453705, 1189453606, 1189453681, 1189453594, 1189453638, 1189453709, 1189453603, 1189453586, 1189453721, 1189453608, 1189453657, 1189453725, 1189453610, 1189453687, 1189453601], "tags": {"amenity": "parking", "fee": "no", "name": "Parking T.I.R. (Transport International Routier)", "park_ride": "yes", "parking": "surface"}}, {"type": "way", "id": 103009734, "nodes": [1189453664, 1189453732, 1189453612, 1189453691, 1189453600, 1189453646, 1189453664], "tags": {"amenity": "parking", "capacity:disabled": "yes", "fee": "no", "park_ride": "no", "parking": "surface"}}, {"type": "way", "id": 144376628, "nodes": [1579281189, 1579281170, 1579281171, 6402424824, 1579281191, 1579281189], "tags": {"amenity": "parking", "parking": "surface"}}, {"type": "way", "id": 144382781, "nodes": [1579328523, 11813359116, 11813359118, 11813359117, 1579328511, 2918944229, 1579328506, 11780020145, 2918944234, 1579328507, 1579328508, 1579328523], "tags": {"access": "private", "amenity": "parking", "parking": "surface"}}, {"type": "way", "id": 178877613, "nodes": [1892331381, 1892331378, 1892331390, 1892331375, 1892331381], "tags": {"amenity": "parking", "parking": "surface"}}, {"type": "way", "id": 178877614, "nodes": [1892331400, 1892331341, 1892331350, 1892331347, 1892331400], "tags": {"amenity": "parking", "parking": "surface"}}, {"type": "way", "id": 178877615, "nodes": [1892331309, 1892331338, 1892331313, 1892331337, 1892331309], "tags": {"amenity": "parking", "parking": "surface"}}, {"type": "way", "id": 183639758, "nodes": [1940503453, 1940503543, 1940503541, 1940503514, 1940503572, 1940503633, 1940503585, 1940503478, 1940503453], "tags": {"access": "no", "amenity": "parking", "capacity": "11", "parking": "surface"}}, {"type": "way", "id": 183639762, "nodes": [1940503510, 1940503489, 1940503657, 1940503601, 1940503455, 1940503510], "tags": {"access": "no", "amenity": "parking", "capacity": "13", "parking": "surface"}}, {"type": "way", "id": 183639765, "nodes": [1940503616, 1940503458, 1940503523, 1940503658, 1940503587, 1940503670, 1940503616], "tags": {"access": "no", "amenity": "parking", "capacity": "8", "parking": "surface"}}, {"type": "way", "id": 183639770, "nodes": [1940503485, 1940503496, 1940503664, 357561915, 357561913, 357561910, 1940503485], "tags": {"access": "no", "amenity": "parking", "parking": "surface"}}, {"type": "way", "id": 183639771, "nodes": [1940503507, 1940503699, 1940503687, 1940503557, 1940503507], "tags": {"amenity": "parking", "parking": "surface"}}, {"type": "way", "id": 183639776, "nodes": [1940503675, 1940503525, 1940503538, 1940503660, 1940503614, 1940503675], "tags": {"amenity": "parking", "parking": "surface"}}, {"type": "way", "id": 184079967, "nodes": [1945168916, 1945168898, 1945168915, 1945168917, 1945168932, 1945168916], "tags": {"amenity": "parking", "name": "Parking CICE"}}, {"type": "way", "id": 184081099, "nodes": [1945202737, 1945202745, 1560717242, 1945202769, 1945202791, 1945202823, 1945202737], "tags": {"amenity": "parking", "parking": "surface"}}, {"type": "way", "id": 187200023, "nodes": [1979445386, 1979445398, 1979445357, 1979445349, 1979445386], "tags": {"amenity": "parking", "parking": "surface"}}, {"type": "way", "id": 187200028, "nodes": [1979445366, 1979445400, 1979445394, 1979445364, 1979445366], "tags": {"amenity": "parking", "parking": "surface"}}, {"type": "way", "id": 228994843, "nodes": [2376370496, 2376370491, 2376370497, 2376370502, 2376370470, 2376370500, 2376370464, 2376370492, 2376370482, 2376370548, 2376370534, 2376370531, 2376370489, 2376370496], "tags": {"amenity": "parking", "fee": "no", "name": "Parking T.I.R. (Transport International Routier)", "park_ride": "yes", "parking": "surface"}}, {"type": "way", "id": 228994847, "nodes": [2376370537, 2376370522, 1579271747, 2376370479, 2376370537], "tags": {"amenity": "parking", "fee": "no", "name": "Parking T.I.R. (Transport International Routier)", "park_ride": "yes", "parking": "surface"}}, {"type": "way", "id": 228995473, "nodes": [2376375568, 2376375575, 2376375583, 1579271743, 2376375578, 2376375568], "tags": {"amenity": "parking", "fee": "no", "name": "Parking T.I.R. (Transport International Routier)", "park_ride": "yes", "parking": "surface", "source": "Maps4BW"}}, {"type": "way", "id": 228995475, "nodes": [1579271745, 2376375574, 2376375584, 2376375586, 1579271745], "tags": {"amenity": "parking", "fee": "no", "name": "Parking T.I.R. (Transport International Routier)", "park_ride": "yes", "parking": "surface"}}, {"type": "way", "id": 228996011, "nodes": [2376380416, 2376380420, 3769058726, 2376380387, 2376380391, 2376380416], "tags": {"amenity": "parking", "parking": "surface"}}, {"type": "way", "id": 228996014, "nodes": [2376380380, 2376380382, 2376380422, 2376380425, 2376380390, 2376380393, 2376380374, 1559474875, 1559474699, 3770111747, 1559474486, 1559474524, 1559474231, 2376380424, 6627801408, 6627801413, 2376380398, 2376380380], "tags": {"amenity": "parking", "parking": "surface"}}, {"type": "way", "id": 228996016, "nodes": [2376380360, 2376380350, 5138653435, 2376380410, 2376380413, 2376380414, 2376380415, 2376380365, 2376380364, 2376380362, 2376380360], "tags": {"amenity": "parking", "parking": "surface"}}, {"type": "way", "id": 228996912, "nodes": [2376388457, 2376388459, 6576981229, 2376388449, 6628627556, 2376388447, 2376388457], "tags": {"amenity": "parking", "parking": "surface"}}, {"type": "way", "id": 238620505, "nodes": [2464320815, 2464320816, 2464320818, 2464320820, 2464320827, 2464320815], "tags": {"amenity": "parking", "parking": "surface"}}, {"type": "way", "id": 238804376, "nodes": [2466017446, 2466017449, 2466017451, 2466017453, 2466017455, 2466017457, 2466017459, 4128465238, 4128465236, 2466017461, 2466017484, 2466017483, 6372064548, 6372064549, 6372064550, 2466017464, 2466017466, 4128465244, 2466017468, 2466017470, 6180499282, 2466017472, 2466017446], "tags": {"access": "customers", "amenity": "parking", "parking": "surface"}}, {"type": "way", "id": 238804381, "nodes": [2466017501, 2466017502, 2466017503, 6191236725, 4499158180, 2466017501], "tags": {"access": "private", "amenity": "parking", "parking": "surface"}}, {"type": "way", "id": 255890281, "nodes": [2616036516, 2616036523, 2616036517, 2616036518, 2616036519, 2616036520, 2616036521, 2616036522, 2616036516], "tags": {"access": "yes", "amenity": "parking", "fee": "yes", "parking": "surface"}}, {"type": "way", "id": 332074532, "nodes": [1892331396, 1892331339, 3391859978, 3391859979, 3391859980, 1892331396], "tags": {"amenity": "parking", "capacity": "5", "parking": "surface"}}, {"type": "way", "id": 332074534, "nodes": [3391859990, 3391859991, 3391859992, 1911101327, 3793321251, 3391859990], "tags": {"amenity": "parking", "parking": "surface"}}, {"type": "way", "id": 332125059, "nodes": [3392455237, 3392455230, 3392455233, 3392455239, 3392455237], "tags": {"amenity": "parking", "parking": "surface"}}, {"type": "way", "id": 332126055, "nodes": [3392462336, 3392462334, 3793321252, 299854016, 3392462343, 3392462336], "tags": {"access": "no", "amenity": "parking", "parking": "surface"}}, {"type": "way", "id": 332126056, "nodes": [3392462335, 3392462333, 3392462339, 3392462341, 3392462335], "tags": {"amenity": "parking", "parking": "surface"}}, {"type": "way", "id": 332126057, "nodes": [3392462331, 3392462329, 3392462332, 3392462338, 3392462331], "tags": {"access": "no", "amenity": "parking", "parking": "surface"}}, {"type": "way", "id": 332126058, "nodes": [3392462351, 3392462345, 3392462347, 3392462344, 3392462346, 3392462348, 3392462350, 3392462352, 3392462351], "tags": {"amenity": "parking", "parking": "surface"}}, {"type": "way", "id": 332127980, "nodes": [3392485701, 4890221779, 3392485697, 3392485696, 4890221781, 3392485695, 3392485392, 3392485694, 3392485693, 3392485391, 3392485390, 3392485699, 3392485698, 3392485700, 3392485701], "tags": {"access": "no", "amenity": "parking", "parking": "surface"}}, {"type": "way", "id": 332127981, "nodes": [3392485714, 3392485713, 3392485715, 3392485716, 3392485714], "tags": {"amenity": "parking", "capacity": "7", "capacity:disabled": "2", "parking": "surface"}}, {"type": "way", "id": 332127982, "nodes": [3392485712, 4890221739, 3392485706, 3392485702, 309169876, 6627800178, 3392485711, 3392485712], "tags": {"amenity": "parking", "capacity": "9", "capacity:disabled": "2", "parking": "surface"}}, {"type": "way", "id": 332127983, "nodes": [3392485710, 3392485708, 3392485707, 4890221760, 4890221758, 3392485709, 3392485710], "tags": {"access": "no", "amenity": "parking", "parking": "surface"}}, {"type": "way", "id": 422013162, "nodes": [4217355225, 4217355226, 4217355227, 4217355228, 4217355237, 4217355225], "tags": {"access": "no", "amenity": "parking", "capacity": "12", "parking": "surface"}}, {"type": "way", "id": 422013163, "nodes": [4217355229, 4217355230, 4217355231, 357561889, 4217355229], "tags": {"access": "no", "amenity": "parking", "capacity": "4", "parking": "surface"}}, {"type": "way", "id": 422013164, "nodes": [4217355233, 4217355234, 4217355235, 4217355236, 4217355233], "tags": {"access": "no", "amenity": "parking", "capacity": "6", "parking": "surface"}}, {"type": "way", "id": 422013166, "nodes": [4217355245, 4217355246, 4217355247, 4217355248, 4217355245], "tags": {"access": "no", "amenity": "parking", "capacity": "12", "parking": "surface"}}, {"type": "way", "id": 422013170, "nodes": [4217355255, 4217355256, 4217355257, 4217355258, 10967894005, 4217355255], "tags": {"amenity": "parking", "name": "Parking Speedy", "parking": "surface"}}, {"type": "way", "id": 422013176, "nodes": [4217355275, 4217355276, 4217355277, 4217355278, 4217355279, 6191236728, 4217355280, 4217355281, 4217355282, 4217355283, 4217355284, 4217355285, 8072598504, 4217355286, 4217355287, 1259891366, 4217355275], "tags": {"access": "no", "amenity": "parking", "name": "Parking Novartis", "name:de": "WSJ-390", "operator": "WSJ-390", "parking": "surface"}}, {"type": "way", "id": 528896336, "nodes": [5138626783, 5138626764, 5138626765, 5138626766, 5138626767, 5138626768, 5138626769, 5138626770, 5138626771, 5138626772, 5138626773, 5138626774, 5138626775, 5138626784, 5138626780, 5138626779, 5138626783], "tags": {"access": "no", "amenity": "parking", "operator": "Ammann Sander", "parking": "surface"}}, {"type": "way", "id": 531563124, "nodes": [5159878519, 5159878474, 5159878701, 5159878680, 5159878625, 5159878518, 5159878519], "tags": {"access": "no", "amenity": "parking", "operator": "Novartis", "parking": "surface", "ref": "WSJ-396 (PP4)", "source": "KTBASELSTADT2015"}}, {"type": "way", "id": 549615592, "nodes": [5309079621, 5309079622, 8851515158, 5309079629, 5309079628, 5309079627, 5309079626, 5309079625, 5309079623, 5309079624, 8427811585, 5309079621], "tags": {"access": "permissive", "amenity": "parking", "parking": "street_side"}}, {"type": "way", "id": 590867351, "nodes": [5640481860, 5640481861, 5640481862, 5640481863, 5640481864, 5640481865, 5640481866, 5640481867, 5640481868, 5640481869, 5640481870, 5640481871, 5640481872, 5640481873, 5640481874, 5640481860], "tags": {"access": "private", "amenity": "parking", "parking": "surface"}}, {"type": "way", "id": 705036861, "nodes": [6621885481, 6621885482, 6621885483, 6621885484, 6621914385, 6621914386, 6621914387, 8427811566, 8427811559, 6621885481], "tags": {"amenity": "parking", "operator": "UPK", "operator:type": "private", "parking": "street_side"}}, {"type": "way", "id": 705458026, "nodes": [6627808533, 6627808532, 6627808531, 6627808530, 6627808533], "tags": {"amenity": "parking", "capacity": "4", "parking": "surface"}}, {"type": "way", "id": 804304823, "nodes": [7523152172, 7523152171, 7523152170, 7523152169, 7523152168, 7523152167, 7523152172], "tags": {"access": "private", "amenity": "parking", "capacity": "65", "parking": "surface", "surface": "asphalt"}}, {"type": "way", "id": 925538732, "nodes": [8589530628, 8589530627, 8589530626, 8589530625, 8589530631, 8589530629, 8589530630, 2685205575, 2685205578, 8589530624, 8589530628], "tags": {"access": "customers", "amenity": "parking", "fee": "no", "parking": "surface", "surface": "asphalt"}}, {"type": "way", "id": 1080291230, "nodes": [9901987683, 9929220692, 9929220693, 9901987684, 9901987685, 9901987686, 9901987683], "tags": {"access": "private", "amenity": "parking", "capacity": "220", "capacity:disabled": "0", "fee": "no", "operator": "Sun Chemicals", "operator:type": "business", "parking": "surface", "surface": "asphalt"}}, {"type": "way", "id": 1227660633, "nodes": [11384407287, 11384407288, 11384407289, 11384407290, 11384407291, 11384407292, 11384407293, 11384407294, 11384407295, 11384407296, 11384407297, 11384407298, 11384407287], "tags": {"access": "private", "amenity": "parking", "capacity": "7"}}, {"type": "way", "id": 1268319588, "nodes": [11780020146, 11780020147, 11780020148, 11780020149, 11780020150, 11780020151, 11780020152, 11780020146], "tags": {"access": "customers", "amenity": "parking", "fee": "no", "parking": "surface"}}, {"type": "way", "id": 1272167409, "nodes": [11813400116, 11813400117, 11813400118, 11813400119, 11813400120, 11813400121, 11813400122, 11813400123, 11813400124, 11813400116], "tags": {"access": "private", "amenity": "parking"}}, {"type": "way", "id": 1308424719, "nodes": [726285689, 12116745509, 12116745510, 12116745511, 726285689], "tags": {"access": "yes", "amenity": "parking", "capacity": "8", "fee": "no", "parking": "surface"}}, {"type": "way", "id": 1308591674, "nodes": [12118356089, 12118356090, 12118356091, 12118356092, 12118356089], "tags": {"amenity": "parking", "capacity": "2", "orientation": "parallel", "parking": "street_side"}}, {"type": "way", "id": 1308591675, "nodes": [12118356093, 12118356094, 12118356095, 12118356096, 12118356093], "tags": {"amenity": "parking", "capacity": "3", "orientation": "parallel", "parking": "street_side"}}, {"type": "way", "id": 1308591676, "nodes": [12118356097, 12118356098, 12118356099, 12118356100, 12118356097], "tags": {"amenity": "parking", "capacity": "3", "orientation": "parallel", "parking": "street_side"}}, {"type": "way", "id": 1308591677, "nodes": [12118384801, 12118384802, 12118384803, 12118384804, 12118384801], "tags": {"amenity": "parking", "capacity": "3", "orientation": "parallel", "parking": "street_side"}}, {"type": "way", "id": 1308591678, "nodes": [12118384805, 12118384809, 12118384806, 12118384810, 12118384807, 12118384808, 12118384805], "tags": {"amenity": "parking", "capacity": "4", "orientation": "parallel", "parking": "street_side"}}, {"type": "way", "id": 1308591679, "nodes": [12118384811, 12118384812, 12118384813, 12118384814, 12118384811], "tags": {"amenity": "parking", "capacity": "1", "orientation": "parallel", "parking": "street_side"}}, {"type": "way", "id": 1308591680, "nodes": [12118384815, 12118384816, 12118384817, 12118384818, 12118384815], "tags": {"amenity": "parking", "capacity": "2", "orientation": "parallel", "parking": "street_side"}}, {"type": "way", "id": 1308591683, "nodes": [11880919499, 12118384825, 12118384826, 12118384824, 11880919499], "tags": {"amenity": "parking", "orientation": "parallel", "parking": "street_side"}}, {"type": "way", "id": 1308591684, "nodes": [12118384827, 12118384828, 12118384829, 12118384830, 12118384827], "tags": {"amenity": "parking", "orientation": "parallel", "parking": "street_side"}}, {"type": "way", "id": 1308591685, "nodes": [12118384848, 12118384849, 12118384850, 12118384851, 12118384848], "tags": {"amenity": "parking", "orientation": "parallel", "parking": "street_side"}}, {"type": "way", "id": 1308591686, "nodes": [12118384852, 12118384853, 12118384854, 12118384855, 12118384852], "tags": {"amenity": "parking", "orientation": "parallel", "parking": "street_side"}}, {"type": "way", "id": 1308591687, "nodes": [12118384856, 12118384857, 12118384858, 12118384859, 12118384856], "tags": {"amenity": "parking", "orientation": "parallel", "parking": "street_side"}}, {"type": "way", "id": 1308591688, "nodes": [12118384860, 12118384861, 12118384862, 12118384863, 12118384860], "tags": {"amenity": "parking", "orientation": "parallel", "parking": "street_side"}}, {"type": "way", "id": 1308591689, "nodes": [12118384864, 12118384865, 12118384866, 12118384867, 12118384864], "tags": {"amenity": "parking", "orientation": "parallel", "parking": "street_side"}}, {"type": "way", "id": 1308591690, "nodes": [12118384868, 12118384869, 12118384870, 12118384871, 12118384868], "tags": {"amenity": "parking", "orientation": "parallel", "parking": "street_side"}}, {"type": "way", "id": 1308591692, "nodes": [12118384872, 12118384876, 12118384877, 12118384873, 12118384872], "tags": {"amenity": "parking", "orientation": "parallel", "parking": "street_side"}}, {"type": "way", "id": 1321664903, "nodes": [12230151687, 12230151688, 12230151689, 12230151692, 12230151690, 12230151687], "tags": {"amenity": "parking"}}, {"type": "way", "id": 1348559074, "nodes": [12474247785, 12474247786, 12474247787, 12474247788, 12474247789, 12474247790, 12474247785], "tags": {"access": "private", "amenity": "parking"}}, {"type": "way", "id": 1387477855, "nodes": [12843796396, 12843796397, 12843796398, 12843796399, 12843833747, 12843796400, 12843833701, 12843833752, 12843833702, 12843833703, 12843833704, 12843833705, 12843833749, 12843833748, 12843833750, 12843833706, 12843833751, 12843833707, 12843833708, 12843833709, 12843833753, 12843833710, 12843833711, 12843833712, 12843833713, 12843833714, 12843833715, 12843833716, 12843833717, 12843833754, 12843833718, 12843833719, 12843833720, 12843833721, 12843833722, 12843833723, 12843833724, 12843833725, 12843833726, 12843833727, 12843833728, 12843833729, 12843833730, 12843833731, 12843833732, 12843833733, 12843833734, 12843833735, 12843833736, 12843833737, 12843833738, 12843833739, 12843833740, 12843833741, 12843833742, 12843833743, 12843833744, 12843833745, 12843833746, 12843796396]}, {"type": "way", "id": 1387477856, "nodes": [12843833755, 12843833756, 12843833757, 12843833758, 12843833755]}, {"type": "way", "id": 1387477857, "nodes": [12843833759, 12843833760, 12843833761, 12843833762, 12843833763, 12843833764, 12843833765, 12843833766, 12843833767, 12843833768, 12843833769, 12843833770, 12843833771, 12843833772, 12843833773, 12843833774, 12843833775, 12843833776, 12843833777, 12843833759]}, {"type": "way", "id": 1387508376, "nodes": [12844080716, 12844080717, 12844080718, 12844080719, 12844080716], "tags": {"amenity": "parking", "capacity": "1", "capacity:disabled": "1", "orientation": "parallel", "parking": "street_side"}}, {"type": "way", "id": 1392517956, "nodes": [12890332091, 12890332092, 12890332093, 12890332094, 12890332095, 12890332096, 12890332097, 12890332098, 12890332099, 12890332100, 12890337701, 12890337702, 12890337703, 12890332091], "tags": {"amenity": "parking"}}, {"type": "way", "id": 1395582599, "nodes": [12918045895, 12918045896, 12918045897, 12918045898, 12918045895], "tags": {"access": "private", "amenity": "parking", "orientation": "perpendicular", "parking": "street_side"}}, {"type": "way", "id": 1395582600, "nodes": [12918045899, 12918045900, 12918062101, 12918062102, 12918045899], "tags": {"access": "private", "amenity": "parking", "orientation": "perpendicular", "parking": "street_side"}}, {"type": "relation", "id": 19141406, "members": [{"type": "way", "ref": 1387477855, "role": "outer"}, {"type": "way", "ref": 1387477856, "role": "inner"}, {"type": "way", "ref": 1387477857, "role": "inner"}], "tags": {"amenity": "parking", "parking": "surface", "type": "multipolygon"}}]}